AcousticExport/__init__.py
AcousticExport/processing.py
AcousticExport/utils.py
AcousticExport-0.0.3.dist-info/METADATA
AcousticExport-0.0.3.dist-info/WHEEL
AcousticExport-0.0.3.dist-info/entry_points.txt
AcousticExport-0.0.3.dist-info/top_level.txt
AcousticExport-0.0.3.dist-info/RECORD
